pqviewer/__init__.py
pqviewer/__main__.py
pqviewer/app.py
pqviewer/cli.py
pqviewer/core/__init__.py
pqviewer/core/file_parser.py
pqviewer/exceptions/__init__.py
pqviewer/exceptions/exceptions.py
pqviewer/global.tcss
pqviewer/views/__init__.py
pqviewer/views/help_screen.py
pqviewer/views/table_content.py
pqviewer/views/table_footer.py
pqviewer/views/table_header.py
pqviewer/views/table_schema.py
pqviewer/views/themes_screen.py
pqviewer-0.2.9.dist-info/LICENSE
pqviewer-0.2.9.dist-info/METADATA
pqviewer-0.2.9.dist-info/WHEEL
pqviewer-0.2.9.dist-info/entry_points.txt
pqviewer-0.2.9.dist-info/RECORD
