Metadata-Version: 2.1
Name: pqviewer
Version: 0.2.9
Summary: View Apache Parquet Files In Your Terminal
Home-page: https://github.com/thread53/pqviewer
License: MIT
Author: thread53
Author-email: thread53@users.noreply.github.com
Requires-Python: >=3.8,<4.0
Classifier: Development Status :: 5 - Production/Stable
Classifier: Environment :: Console
Classifier: License :: OSI Approved :: MIT License
Classifier: Programming Language :: Python :: 3
Classifier: Programming Language :: Python :: 3.8
Classifier: Programming Language :: Python :: 3.9
Classifier: Programming Language :: Python :: 3.10
Classifier: Programming Language :: Python :: 3.11
Classifier: Programming Language :: Python :: 3.12
Classifier: Programming Language :: Python :: 3.13
Requires-Dist: pyarrow (>=17.0.0)
Requires-Dist: textual (==0.46.0)
Project-URL: Repository, https://github.com/thread53/pqviewer
